{
  "notes": [
    {
      "id": 1,
      "content": "custom-hooks are awesome!"
    },
    {
      "id": 2,
      "content": "best feature ever <3"
    },
    {
      "content": "This is awesome",
      "id": 3
    },
    {
      "content": "Hello Bitch",
      "id": 4
    },
    {
      "content": "Yayyyy",
      "id": 5
    },
    {
      "content": "Helloooooo",
      "id": 6
    },
    {
      "content": "",
      "id": 7
    },
    {
      "content": "Here is my new note",
      "id": 8
    },
    {
      "content": "",
      "id": 9
    },
    {
      "content": "Bitch",
      "id": 10
    },
    {
      "content": "Bitch",
      "id": 11
    },
    {
      "content": "Bitch",
      "id": 12
    },
    {
      "content": "Bitch",
      "id": 13
    }
  ],
  "persons": [
    {
      "id": 1,
      "name": "mluukkai",
      "number": "040-5483923"
    },
    {
      "id": 2,
      "name": "hellas",
      "number": "012-123123"
    },
    {
      "name": "Nikke",
      "number": "43434343",
      "id": 3
    },
    {
      "name": "Yolo mies",
      "number": "040404",
      "id": 4
    }
  ]
}